stream_service/__init__.py
stream_service/client.py
stream_service/server.py
stream_service/examples/__init__.py
stream_service/examples/client_rpc.py
stream_service/examples/run_server.py
stream_service/examples/stream_data.py
stream_service/lib/__init__.py
stream_service/lib/buffer.py
stream_service/lib/frame.py
stream_service/lib/helpers.py
stream_service/lib/rpc.py
stream_service-0.1.0.dist-info/LICENSE
stream_service-0.1.0.dist-info/METADATA
stream_service-0.1.0.dist-info/WHEEL
stream_service-0.1.0.dist-info/top_level.txt
stream_service-0.1.0.dist-info/RECORD
