Metadata-Version: 2.1
Name: stream-service
Version: 0.1.0
Summary: Client/Server implementation for data streaming in channels based on python >= 3.5
Home-page: https://github.com/BR1py/stream_service
Author: B_R
Author-email: br_development@posteo.org
License: MIT
Platform: UNKNOWN
Classifier: Programming Language :: Python :: 3
Classifier: License :: OSI Approved :: MIT License
Classifier: Operating System :: OS Independent
Requires-Python: >=3.5
License-File: LICENSE
